autolib/AutoLib.py
autolib/__init__.py
autolib_volatile_int-0.0.1.dist-info/LICENSE
autolib_volatile_int-0.0.1.dist-info/METADATA
autolib_volatile_int-0.0.1.dist-info/WHEEL
autolib_volatile_int-0.0.1.dist-info/top_level.txt
autolib_volatile_int-0.0.1.dist-info/RECORD
