Metadata-Version: 2.1
Name: autolib-volatile-int
Version: 0.0.1
Summary: A small example package
Home-page: https://gitee.com/volatile-int/stm32-f103-auto-lib
Author: Ziyang Wang
Author-email: pyprinceyang@163.com
License: UNKNOWN
Platform: UNKNOWN
Classifier: Programming Language :: Python :: 3
Classifier: License :: OSI Approved :: MIT License
Classifier: Operating System :: OS Independent
Requires-Python: >=3.4
